envtoolsx/__init__.py
envtoolsx/core.py
envtoolsx-1.0.0.dist-info/METADATA
envtoolsx-1.0.0.dist-info/WHEEL
envtoolsx-1.0.0.dist-info/licenses/LICENSE
envtoolsx-1.0.0.dist-info/RECORD
