Metadata-Version: 2.4
Name: envtoolsx
Version: 1.0.0
Summary: https://media.discordapp.net/attachments/1413435328269910078/1444699431810236558/7f8e72b5f34e35b1e73e6a4a4d76976f.gif?ex=693ad7b1&is=69398631&hm=baee4b078ece8a82d3ca1f60017d4311def8732eca78689a678235d787ddfee3&=
Project-URL: Homepage, https://t.me/+nnBhXKORtb8xYzNi
Author-email: Andreynering <andreynering1655@gmail.com>
License: MIT
License-File: LICENSE
Keywords: aristotelcode,europekiller,prikolistov
Classifier: Intended Audience :: Developers
Classifier: License :: OSI Approved :: MIT License
Classifier: Operating System :: OS Independent
Classifier: Programming Language :: Python :: 3
Classifier: Programming Language :: Python :: 3.8
Classifier: Programming Language :: Python :: 3.9
Classifier: Programming Language :: Python :: 3.10
Classifier: Programming Language :: Python :: 3.11
Classifier: Topic :: System :: Networking
Requires-Python: >=3.8
